{"schema_version":"1.0","match_id":"WC2026-GRP-CAN-BIH","match":"Canada vs Bosnia","date":"2026-06-13","competition":"FIFA World Cup 2026","stage":"Group Stage","status":"COMPLETED","quality_grade":"Gold","immutable":true,"score":{"ht":"0-1","ft":"1-1"},"markets":[{"market_code":"AH","selection":"Canada -0.50","opening_odds":1.77,"closing_odds":1.77,"movement_pct":0.0,"result":"Archived"},{"market_code":"AH","selection":"Bosnia +0.50","opening_odds":2.0,"closing_odds":1.97,"movement_pct":-1.5,"result":"Archived"},{"market_code":"1X2","selection":"Canada","opening_odds":1.77,"closing_odds":1.77,"movement_pct":0.0,"result":"Archived"},{"market_code":"1X2","selection":"Draw","opening_odds":3.2,"closing_odds":3.1,"movement_pct":-3.1,"result":"Archived"},{"market_code":"1X2","selection":"Bosnia","opening_odds":4.1,"closing_odds":4.1,"movement_pct":0.0,"result":"Archived"},{"market_code":"OU","selection":"Over 2.5","opening_odds":2.15,"closing_odds":2.1,"movement_pct":-2.3,"result":"Archived"},{"market_code":"OU","selection":"Under 2.5","opening_odds":1.6,"closing_odds":1.63,"movement_pct":1.9,"result":"Archived"},{"market_code":"BTTS","selection":"Yes","opening_odds":1.95,"closing_odds":1.95,"movement_pct":0.0,"result":"Archived"},{"market_code":"BTTS","selection":"No","opening_odds":1.7,"closing_odds":1.7,"movement_pct":0.0,"result":"Archived"}],"derived_features":{"actual_winner":"Draw","actual_first_half_winner":"Bosnia","actual_total_goals":2,"actual_btts":true,"spwin_training_notes":"Batch 4 historical Gold expansion from SGOdds past odds. Data collection only; no replay or model changes."},"provenance":{"source":"SGOdds past odds page","source_url":"https://sgodds.com/football/results-past-odds/Canada-vs-Bosnia-139951","archive_policy":"Rule 7 immutable historical data","builder":"Gold Record Builder v1.0","version":"v1.0","created_on":"2026-07-02"}}